costcla/__init__.py
costcla/datasets/__init__.py
costcla/datasets/base.py
costcla/datasets/data/bankmarketing.csv.gz
costcla/datasets/data/churn_tv_subscriptions.csv.gz
costcla/datasets/data/creditscoring1.csv.gz
costcla/datasets/data/creditscoring2.csv.gz
costcla/datasets/descr/bankmarketing.rst
costcla/datasets/descr/churn_tv_subscriptions.rst
costcla/datasets/descr/creditscoring1.rst
costcla/datasets/descr/creditscoring2.rst
costcla/metrics/__init__.py
costcla/metrics/costs.py
costcla/models/__init__.py
costcla/models/bagging.py
costcla/models/cost_ensemble.py
costcla/models/cost_tree.py
costcla/models/directcost.py
costcla/models/regression.py
costcla/probcal/__init__.py
costcla/probcal/probcal.py
costcla/sampling/__init__.py
costcla/sampling/_smote.py
costcla/sampling/cost_sampling.py
costcla/sampling/sampling.py
costcla/utils/__init__.py
costcla/utils/cross_validation.py
costcla-0.6.dist-info/LICENCE
costcla-0.6.dist-info/METADATA
costcla-0.6.dist-info/WHEEL
costcla-0.6.dist-info/top_level.txt
costcla-0.6.dist-info/RECORD
