Metadata-Version: 2.1
Name: costcla
Version: 0.6
Summary: costcla is a Python module for cost-sensitive machine learning (classification) 
Home-page: https://github.com/albahnsen/CostSensitiveClassification
Author: Alejandro CORREA BAHNSEN
Author-email: al.bahnsen@gmail.com
License: new BSD
Keywords: machine learning,classification,cost-sensitive
Platform: UNKNOWN
Classifier: Intended Audience :: Science/Research
Classifier: Intended Audience :: Developers
Classifier: Programming Language :: Python
Classifier: Topic :: Software Development
Classifier: Topic :: Scientific/Engineering
Classifier: Programming Language :: Python :: 2.7
Classifier: Programming Language :: Python :: 3
Classifier: Programming Language :: Python :: 3.3
Classifier: Programming Language :: Python :: 3.4
Classifier: Programming Language :: Python :: 3.5
Classifier: Topic :: Scientific/Engineering :: Artificial Intelligence
Classifier: License :: OSI Approved :: BSD License
Classifier: Operating System :: OS Independent
Requires-Dist: scikit-learn (>=0.15.0b2)
Requires-Dist: pandas (>=0.14.0)
Requires-Dist: numpy (>=1.8.0)
Requires-Dist: pyea (>=0.2)
